iQore/__init__.py
iQore/iQD_Optimizer_Demo.py
iQore/inject.py
iQore/service.py
iQore/iQD/__init__.py
iQore/iQD/api.py
iqore-0.9.7.3.dist-info/licenses/LICENSE.md
pyarmor_runtime_006585/.pyarmor.ikey
pyarmor_runtime_006585/__init__.py
pyarmor_runtime_006585/darwin_aarch64/.pyarmor.ikey
pyarmor_runtime_006585/darwin_aarch64/pyarmor_runtime.so
pyarmor_runtime_006585/darwin_x86_64/pyarmor_runtime.so
pyarmor_runtime_006585/linux_x86_64/pyarmor_runtime.so
pyarmor_runtime_006585/windows_x86_64/pyarmor_runtime.pyd
iqore-0.9.7.3.dist-info/METADATA
iqore-0.9.7.3.dist-info/WHEEL
iqore-0.9.7.3.dist-info/top_level.txt
iqore-0.9.7.3.dist-info/RECORD
