Metadata-Version: 2.4
Name: iQore
Version: 0.9.7.3
Summary: Secure cloud-optimized quantum SDK
Author-email: "iQore, Inc." <team@iqore.com>
License-Expression: MIT
Keywords: quantum,optimizer,hybrid,cryptography,injection,sdk
Classifier: Development Status :: 4 - Beta
Classifier: Intended Audience :: Developers
Classifier: Intended Audience :: Science/Research
Classifier: Programming Language :: Python :: 3.10
Classifier: Operating System :: OS Independent
Classifier: Topic :: Software Development :: Libraries
Classifier: Topic :: Scientific/Engineering :: Information Analysis
Requires-Python: ==3.10.*
License-File: LICENSE.md
Requires-Dist: requests>=2.27
Requires-Dist: cryptography>=39.0
Dynamic: license-file
